xymon_client/__init__.py
xymon_client/__main__.py
xymon_client/helpers.py
xymon_client-1.0.0.dist-info/LICENSE
xymon_client-1.0.0.dist-info/METADATA
xymon_client-1.0.0.dist-info/WHEEL
xymon_client-1.0.0.dist-info/entry_points.txt
xymon_client-1.0.0.dist-info/top_level.txt
xymon_client-1.0.0.dist-info/RECORD
