Metadata-Version: 2.1
Name: xymon-client
Version: 1.0.0
Summary: A minimalist Xymon client library in Python.
Author-email: Romain Dartigues <romain.dartigues@gmail.com>
License: BSD 3-Clause License
Project-URL: repository, https://gitlab.com/romain-dartigues/python-xymon-client
Keywords: bb,BigBrother,xymon
Classifier: Development Status :: 5 - Production/Stable
Classifier: Environment :: Console
Classifier: Environment :: Plugins
Classifier: Intended Audience :: Developers
Classifier: Intended Audience :: System Administrators
Classifier: License :: OSI Approved :: BSD License
Classifier: Natural Language :: English
Classifier: Operating System :: OS Independent
Classifier: Programming Language :: Python :: 3
Classifier: Topic :: Software Development :: Libraries :: Python Modules
Classifier: Topic :: System :: Monitoring
Requires-Python: >=3.10
License-File: LICENSE
Provides-Extra: tests
Requires-Dist: coverage (>=6) ; extra == 'tests'
Requires-Dist: pytest (>=7) ; extra == 'tests'
